comfydock_server/__init__.py
comfydock_server/app.py
comfydock_server/docker_utils.py
comfydock_server/py.typed
comfydock_server/server.py
comfydock_server/config/__init__.py
comfydock_server/config/default_config.json
comfydock_server/config/loader.py
comfydock_server/config/schema.py
comfydock_server/routes/__init__.py
comfydock_server/routes/comfyui_routes.py
comfydock_server/routes/dependencies.py
comfydock_server/routes/environment_routes.py
comfydock_server/routes/image_routes.py
comfydock_server/routes/user_settings_routes.py
comfydock_server/routes/websocket_routes.py
comfydock_server-0.3.2.dist-info/METADATA
comfydock_server-0.3.2.dist-info/WHEEL
comfydock_server-0.3.2.dist-info/RECORD
