Metadata-Version: 2.4
Name: comfydock_server
Version: 0.3.2
Summary: ComfyDock Server
Author-email: akatz-ai <katzfeyalex+akatzgh@gmail.com>
Requires-Python: >=3.12
Requires-Dist: comfydock-core>=0.2.2
Requires-Dist: fastapi[all]>=0.115.8
Requires-Dist: pydantic-settings>=2.7.1
Requires-Dist: pydantic>=2.10.6
Requires-Dist: python-dateutil>=2.9.0.post0
Requires-Dist: requests>=2.32.3
Requires-Dist: uvicorn>=0.34.0
